moula/__init__.py
moula/__main__.py
moula/bootstrap.py
moula/firefly.py
moula/indexes.py
moula/merger.py
moula/metrics.py
moula/types.py
moula/utils.py
moula/woob.py
moula-1.1.6.dist-info/METADATA
moula-1.1.6.dist-info/WHEEL
moula-1.1.6.dist-info/RECORD
