Metadata-Version: 2.3
Name: moula
Version: 1.1.6
Summary: 
Requires-Python: >=3.13
Classifier: Programming Language :: Python :: 3
Classifier: Programming Language :: Python :: 3.13
Requires-Dist: daemon-metrics (>=1.0.0)
Requires-Dist: prometheus-client (>=0.21.1)
Requires-Dist: requests (>=2.31)
Requires-Dist: the-conf (>=1.0.1)
Requires-Dist: woob (>=3.7)
